opentelemetry/instrumentation/playwright/__init__.py
opentelemetry/instrumentation/playwright/py.typed
opentelemetry/instrumentation/playwright/targets.py
mvv_opentelemetry_instrumentation_playwright-0.1.4.dist-info/METADATA
mvv_opentelemetry_instrumentation_playwright-0.1.4.dist-info/WHEEL
mvv_opentelemetry_instrumentation_playwright-0.1.4.dist-info/entry_points.txt
mvv_opentelemetry_instrumentation_playwright-0.1.4.dist-info/licenses/LICENSE.md
mvv_opentelemetry_instrumentation_playwright-0.1.4.dist-info/RECORD
