Metadata-Version: 2.4
Name: mvv-opentelemetry-instrumentation-playwright
Version: 0.1.4
Summary: Automatic tracing and metrics for your Playwright browser automation scripts using OpenTelemetry.
Project-URL: Homepage, https://github.com/multiversal-ventures/mvv-opentelemetry-instrumentation-playwright
Project-URL: Repository, https://github.com/multiversal-ventures/mvv-opentelemetry-instrumentation-playwright
Project-URL: Issues, https://github.com/multiversal-ventures/mvv-opentelemetry-instrumentation-playwright/issues
Project-URL: Changelog, https://github.com/multiversal-ventures/mvv-opentelemetry-instrumentation-playwright/releases
Author-email: Michael-F-Bryan <michael@multiversal.ventures>
License: MIT License
License-File: LICENSE.md
Keywords: instrumentation,metrics,opentelemetry,playwright,tracing
Classifier: License :: OSI Approved :: MIT License
Classifier: Programming Language :: Python :: 3
Classifier: Programming Language :: Python :: 3.12
Classifier: Programming Language :: Python :: 3.13
Requires-Python: >=3.12
Requires-Dist: opentelemetry-api>=1.33.1
Requires-Dist: opentelemetry-instrumentation>=0.54b1
Requires-Dist: playwright<2.0.0,>=1.52.0
